{
  "frames": [
    {
      "path": "frame_000.png",
      "state": {
        "open": false
      }
    },
    {
      "path": "frame_001.png",
      "state": {
        "open": true,
        "scroll_idx": 0
      }
    },
    {
      "path": "frame_002.png",
      "state": {
        "open": true,
        "scroll_idx": 1
      }
    },
    {
      "path": "frame_003.png",
      "state": {
        "open": true,
        "scroll_idx": 2
      }
    },
    {
      "path": "frame_004.png",
      "state": {
        "open": true,
        "scroll_idx": 3
      }
    },
    {
      "path": "frame_005.png",
      "state": {
        "open": true,
        "scroll_idx": 4
      }
    },
    {
      "path": "frame_006.png",
      "state": {
        "open": true,
        "scroll_idx": 5
      }
    }
  ],
  "actions": [
    {
      "frame": 0,
      "type": "click",
      "x": 244,
      "y": 97
    },
    {
      "frame": 1,
      "type": "move",
      "points": [
        [
          242,
          95,
          0.0
        ],
        [
          247,
          100,
          0.041666666666666664
        ],
        [
          254,
          105,
          0.08333333333333333
        ],
        [
          257,
          108,
          0.125
        ],
        [
          262,
          111,
          0.16666666666666666
        ],
        [
          267,
          117,
          0.20833333333333334
        ],
        [
          268,
          117,
          0.25
        ],
        [
          271,
          125,
          0.2916666666666667
        ],
        [
          277,
          126,
          0.3333333333333333
        ],
        [
          280,
          130,
          0.375
        ],
        [
          286,
          134,
          0.4166666666666667
        ],
        [
          288,
          135,
          0.4583333333333333
        ],
        [
          294,
          140,
          0.5
        ],
        [
          298,
          145,
          0.5416666666666666
        ],
        [
          304,
          146,
          0.5833333333333334
        ],
        [
          305,
          150,
          0.625
        ],
        [
          311,
          154,
          0.6666666666666666
        ],
        [
          314,
          157,
          0.7083333333333334
        ],
        [
          319,
          163,
          0.75
        ],
        [
          323,
          168,
          0.7916666666666666
        ],
        [
          327,
          169,
          0.8333333333333334
        ],
        [
          334,
          174,
          0.875
        ],
        [
          339,
          177,
          0.9166666666666666
        ],
        [
          342,
          183,
          0.9583333333333334
        ],
        [
          345,
          185,
          1.0
        ]
      ]
    },
    {
      "frame": 2,
      "type": "scroll",
      "amount": 1
    },
    {
      "frame": 3,
      "type": "scroll",
      "amount": 1
    },
    {
      "frame": 4,
      "type": "scroll",
      "amount": 1
    },
    {
      "frame": 5,
      "type": "scroll",
      "amount": 1
    },
    {
      "frame": 6,
      "type": "scroll",
      "amount": 1
    },
    {
      "frame": 6,
      "type": "click",
      "x": 244,
      "y": 241
    }
  ],
  "meta": {
    "opt_h": 28,
    "vis_rows": 5,
    "total_rows": 10
  }
}