{
  "image": "E:\\BOT ANK\\bot\\moje_AI\\yolov8\\FULL BOT\\data\\screen\\raw screen\\Zrzut ekranu 2025-11-15 211637_annot.png",
  "color_histogram": {
    "top": [
      {
        "rgb": [
          248,
          248,
          248
        ],
        "pct": 0.542103
      },
      {
        "rgb": [
          248,
          104,
          104
        ],
        "pct": 0.352806
      },
      {
        "rgb": [
          248,
          8,
          8
        ],
        "pct": 0.048919
      },
      {
        "rgb": [
          248,
          248,
          40
        ],
        "pct": 0.029886
      },
      {
        "rgb": [
          200,
          72,
          88
        ],
        "pct": 0.009407
      },
      {
        "rgb": [
          248,
          152,
          200
        ],
        "pct": 0.006679
      },
      {
        "rgb": [
          152,
          56,
          104
        ],
        "pct": 0.003553
      },
      {
        "rgb": [
          232,
          248,
          24
        ],
        "pct": 0.000896
      }
    ],
    "dominant_pct": 0.5421030524217676,
    "dominant_rgb": [
      248,
      248,
      248
    ]
  },
  "dominant_bg_over_50": true,
  "results": [
    {
      "text": "Jestein:",
      "conf": 0.8675391115248203,
      "text_box": [
        21,
        12,
        58,
        25
      ],
      "has_frame": false,
      "frame_hits": 3,
      "dropdown_box": [
        50,
        2,
        92,
        38
      ],
      "frame_rgb": [
        247,
        248,
        250
      ],
      "laser_endpoints": [
        [
          92,
          18
        ],
        [
          39,
          18
        ],
        [
          39,
          1
        ],
        [
          39,
          66
        ]
      ]
    },
    {
      "text": "Jestem:",
      "conf": 0.9923651473862785,
      "text_box": [
        23,
        31,
        79,
        48
      ],
      "has_frame": false,
      "frame_hits": 0,
      "dropdown_box": null,
      "frame_rgb": null,
      "laser_endpoints": null
    },
    {
      "text": "O koblet",
      "conf": 0.7116330415010452,
      "text_box": [
        53,
        130,
        91,
        140
      ],
      "has_frame": false,
      "frame_hits": 3,
      "dropdown_box": [
        95,
        131,
        105,
        142
      ],
      "frame_rgb": [
        254,
        254,
        34
      ],
      "laser_endpoints": [
        [
          94,
          135
        ],
        [
          72,
          135
        ],
        [
          72,
          128
        ],
        [
          72,
          143
        ]
      ]
    },
    {
      "text": "O wole",
      "conf": 0.9215513865152994,
      "text_box": [
        54,
        195,
        88,
        205
      ],
      "has_frame": false,
      "frame_hits": 0,
      "dropdown_box": null,
      "frame_rgb": null,
      "laser_endpoints": null
    },
    {
      "text": "Tuetowic",
      "conf": 0.6843367200344801,
      "text_box": [
        120,
        218,
        192,
        227
      ],
      "has_frame": false,
      "frame_hits": 3,
      "dropdown_box": [
        126,
        219,
        1013,
        245
      ],
      "frame_rgb": [
        255,
        0,
        0
      ],
      "laser_endpoints": [
        [
          1042,
          222
        ],
        [
          109,
          222
        ],
        [
          156,
          216
        ],
        [
          156,
          245
        ]
      ]
    }
  ],
  "triangles": [],
  "ocr_debug": null
}