{
  "frames": [
    {
      "path": "frame_000.png",
      "state": {
        "open": false
      }
    },
    {
      "path": "frame_001.png",
      "state": {
        "open": true,
        "scroll_idx": 0
      }
    },
    {
      "path": "frame_002.png",
      "state": {
        "open": true,
        "scroll_idx": 1
      }
    },
    {
      "path": "frame_003.png",
      "state": {
        "open": true,
        "scroll_idx": 2
      }
    },
    {
      "path": "frame_004.png",
      "state": {
        "open": true,
        "scroll_idx": 3
      }
    },
    {
      "path": "frame_005.png",
      "state": {
        "open": true,
        "scroll_idx": 4
      }
    },
    {
      "path": "frame_006.png",
      "state": {
        "open": true,
        "scroll_idx": 5
      }
    },
    {
      "path": "frame_007.png",
      "state": {
        "open": true,
        "scroll_idx": 6
      }
    }
  ],
  "actions": [
    {
      "frame": 0,
      "type": "click",
      "x": 368,
      "y": 350
    },
    {
      "frame": 1,
      "type": "move",
      "points": [
        [
          369,
          350,
          0.0
        ],
        [
          373,
          353,
          0.041666666666666664
        ],
        [
          375,
          360,
          0.08333333333333333
        ],
        [
          383,
          364,
          0.125
        ],
        [
          384,
          365,
          0.16666666666666666
        ],
        [
          389,
          371,
          0.20833333333333334
        ],
        [
          392,
          377,
          0.25
        ],
        [
          399,
          382,
          0.2916666666666667
        ],
        [
          403,
          384,
          0.3333333333333333
        ],
        [
          408,
          388,
          0.375
        ],
        [
          410,
          394,
          0.4166666666666667
        ],
        [
          416,
          399,
          0.4583333333333333
        ],
        [
          420,
          402,
          0.5
        ],
        [
          423,
          407,
          0.5416666666666666
        ],
        [
          429,
          409,
          0.5833333333333334
        ],
        [
          436,
          414,
          0.625
        ],
        [
          439,
          419,
          0.6666666666666666
        ],
        [
          440,
          422,
          0.7083333333333334
        ],
        [
          445,
          426,
          0.75
        ],
        [
          450,
          431,
          0.7916666666666666
        ],
        [
          456,
          437,
          0.8333333333333334
        ],
        [
          460,
          439,
          0.875
        ],
        [
          465,
          442,
          0.9166666666666666
        ],
        [
          467,
          447,
          0.9583333333333334
        ],
        [
          471,
          451,
          1.0
        ]
      ]
    },
    {
      "frame": 2,
      "type": "scroll",
      "amount": 1
    },
    {
      "frame": 3,
      "type": "scroll",
      "amount": 1
    },
    {
      "frame": 4,
      "type": "scroll",
      "amount": 1
    },
    {
      "frame": 5,
      "type": "scroll",
      "amount": 1
    },
    {
      "frame": 6,
      "type": "scroll",
      "amount": 1
    },
    {
      "frame": 7,
      "type": "scroll",
      "amount": 1
    },
    {
      "frame": 7,
      "type": "click",
      "x": 368,
      "y": 523
    }
  ],
  "meta": {
    "opt_h": 28,
    "vis_rows": 6,
    "total_rows": 12
  }
}