{
  "frames": [
    {
      "path": "frame_000.png",
      "state": {
        "open": false
      }
    },
    {
      "path": "frame_001.png",
      "state": {
        "open": true,
        "scroll_idx": 0
      }
    },
    {
      "path": "frame_002.png",
      "state": {
        "open": true,
        "scroll_idx": 1
      }
    },
    {
      "path": "frame_003.png",
      "state": {
        "open": true,
        "scroll_idx": 2
      }
    },
    {
      "path": "frame_004.png",
      "state": {
        "open": true,
        "scroll_idx": 3
      }
    },
    {
      "path": "frame_005.png",
      "state": {
        "open": true,
        "scroll_idx": 4
      }
    }
  ],
  "actions": [
    {
      "frame": 0,
      "type": "click",
      "x": 357,
      "y": 363
    },
    {
      "frame": 1,
      "type": "move",
      "points": [
        [
          355,
          365,
          0.0
        ],
        [
          359,
          365,
          0.041666666666666664
        ],
        [
          365,
          372,
          0.08333333333333333
        ],
        [
          366,
          376,
          0.125
        ],
        [
          370,
          376,
          0.16666666666666666
        ],
        [
          369,
          382,
          0.20833333333333334
        ],
        [
          375,
          384,
          0.25
        ],
        [
          378,
          386,
          0.2916666666666667
        ],
        [
          379,
          390,
          0.3333333333333333
        ],
        [
          385,
          396,
          0.375
        ],
        [
          388,
          401,
          0.4166666666666667
        ],
        [
          388,
          401,
          0.4583333333333333
        ],
        [
          390,
          404,
          0.5
        ],
        [
          395,
          412,
          0.5416666666666666
        ],
        [
          395,
          411,
          0.5833333333333334
        ],
        [
          401,
          417,
          0.625
        ],
        [
          401,
          422,
          0.6666666666666666
        ],
        [
          407,
          426,
          0.7083333333333334
        ],
        [
          410,
          430,
          0.75
        ],
        [
          411,
          433,
          0.7916666666666666
        ],
        [
          414,
          436,
          0.8333333333333334
        ],
        [
          415,
          437,
          0.875
        ],
        [
          422,
          441,
          0.9166666666666666
        ],
        [
          422,
          445,
          0.9583333333333334
        ],
        [
          425,
          448,
          1.0
        ]
      ]
    },
    {
      "frame": 2,
      "type": "scroll",
      "amount": 1
    },
    {
      "frame": 3,
      "type": "scroll",
      "amount": 1
    },
    {
      "frame": 4,
      "type": "scroll",
      "amount": 1
    },
    {
      "frame": 5,
      "type": "scroll",
      "amount": 1
    },
    {
      "frame": 5,
      "type": "click",
      "x": 357,
      "y": 505
    }
  ],
  "meta": {
    "opt_h": 28,
    "vis_rows": 5,
    "total_rows": 9
  }
}