{
  "frames": [
    {
      "path": "frame_000.png",
      "state": {
        "open": false
      }
    },
    {
      "path": "frame_001.png",
      "state": {
        "open": true,
        "scroll_idx": 0
      }
    },
    {
      "path": "frame_002.png",
      "state": {
        "open": true,
        "scroll_idx": 1
      }
    },
    {
      "path": "frame_003.png",
      "state": {
        "open": true,
        "scroll_idx": 2
      }
    },
    {
      "path": "frame_004.png",
      "state": {
        "open": true,
        "scroll_idx": 3
      }
    },
    {
      "path": "frame_005.png",
      "state": {
        "open": true,
        "scroll_idx": 4
      }
    },
    {
      "path": "frame_006.png",
      "state": {
        "open": true,
        "scroll_idx": 5
      }
    },
    {
      "path": "frame_007.png",
      "state": {
        "open": true,
        "scroll_idx": 6
      }
    },
    {
      "path": "frame_008.png",
      "state": {
        "open": true,
        "scroll_idx": 7
      }
    }
  ],
  "actions": [
    {
      "frame": 0,
      "type": "click",
      "x": 249,
      "y": 88
    },
    {
      "frame": 1,
      "type": "move",
      "points": [
        [
          249,
          90,
          0.0
        ],
        [
          253,
          92,
          0.041666666666666664
        ],
        [
          258,
          95,
          0.08333333333333333
        ],
        [
          258,
          100,
          0.125
        ],
        [
          264,
          104,
          0.16666666666666666
        ],
        [
          266,
          107,
          0.20833333333333334
        ],
        [
          269,
          111,
          0.25
        ],
        [
          275,
          115,
          0.2916666666666667
        ],
        [
          277,
          120,
          0.3333333333333333
        ],
        [
          280,
          128,
          0.375
        ],
        [
          284,
          128,
          0.4166666666666667
        ],
        [
          287,
          135,
          0.4583333333333333
        ],
        [
          290,
          140,
          0.5
        ],
        [
          296,
          144,
          0.5416666666666666
        ],
        [
          297,
          146,
          0.5833333333333334
        ],
        [
          303,
          149,
          0.625
        ],
        [
          305,
          153,
          0.6666666666666666
        ],
        [
          309,
          160,
          0.7083333333333334
        ],
        [
          313,
          166,
          0.75
        ],
        [
          314,
          167,
          0.7916666666666666
        ],
        [
          320,
          170,
          0.8333333333333334
        ],
        [
          321,
          177,
          0.875
        ],
        [
          327,
          182,
          0.9166666666666666
        ],
        [
          329,
          185,
          0.9583333333333334
        ],
        [
          333,
          188,
          1.0
        ]
      ]
    },
    {
      "frame": 2,
      "type": "scroll",
      "amount": 1
    },
    {
      "frame": 3,
      "type": "scroll",
      "amount": 1
    },
    {
      "frame": 4,
      "type": "scroll",
      "amount": 1
    },
    {
      "frame": 5,
      "type": "scroll",
      "amount": 1
    },
    {
      "frame": 6,
      "type": "scroll",
      "amount": 1
    },
    {
      "frame": 7,
      "type": "scroll",
      "amount": 1
    },
    {
      "frame": 8,
      "type": "scroll",
      "amount": 1
    },
    {
      "frame": 8,
      "type": "click",
      "x": 249,
      "y": 259
    }
  ],
  "meta": {
    "opt_h": 28,
    "vis_rows": 6,
    "total_rows": 13
  }
}